Workbook

Sheet Portfolio
A1: INVESTMENT PORTFOLIO — 5-YEAR PERFORMANCE ANALYSIS
A2: $500,000 across 12 stocks | 2 Sectors (Information Technology & Healthcare) | Purchased Jan 20, 2020 (adjusted for MLK Day holiday) | 50% sold Jan 24, 2025
A3: Total Investment ($): | B3: 500000 | D3: Purchase Date (adjusted*): | E3: 43851 | G3: Sell Date (50%): | H3: 45681 | J3: Tax Rate: | K3: 0.15 | M3: * Jan 20, 2020 was Martin Luther King Jr. Day (federal market holiday); the next trading day, Jan 21, 2020, was used.
A5: Ticker | B5: Sector | C5: Industry | D5: Company Description | E5: Investment % | F5: Investment Amount ($) | G5: Purchase Price (Jan 21, 2020)* | H5: Shares Bought | I5: Purchase Value | J5: Sell Price (Jan 24, 2025) | K5: Value of Sold Shares (50%) | L5: Current Price (Live) | M5: Value of Unsold Shares (50%) | N5: Transaction Fee | O5: Net Gain (after fees) | P5: Tax on Gain (15% realized) | Q5: % Gain Before Tax | R5: % Gain After Tax | S5: Total Current Value ($)*
A6: MSFT | B6: Information Technology | C6: Software—Infrastructure | D6: Microsoft (Information Technology - Software—Infrastructure) develops Windows, the Azure cloud platform, and Office. It leads enterprise cloud infrastructure and generative AI via its OpenAI partnership. | E6: 0.12 | F6: =$B$3*E6 -> 60000 | G6: 157.09 | H6: =ROUND(F6/G6,0) -> 382 | I6: =G6*H6 -> 60008.38 | J6: 438.03 | K6: =0.5*H6*J6 -> 83663.73 | L6: =VLOOKUP(A6,LivePrices!$A$4:$B$15,2,FALSE()) -> 516.17 | M6: =0.5*H6*L6 -> 98588.47 | N6: =IF(H6<=100,10,IF(H6<=200,20,IF(H6<=500,30,50))) -> 30 | O6: =(K6+M6)-(I6+N6) -> 122213.82 | P6: =MAX(0,$K$3*(K6-0.5*I6)) -> 8048.931 | Q6: =O6/I6 -> 2.0366126 | R6: =(O6-P6)/I6 -> 1.9024824 | S6: =K6+M6 -> 182252.2
A7: ORCL | B7: Information Technology | C7: Software—Infrastructure | D7: Oracle (Information Technology - Software—Infrastructure) is best known for relational database software, now expanding into cloud infrastructure (OCI) and enterprise applications for large organizations. | E7: 0.06 | F7: =$B$3*E7 -> 30000 | G7: 50.35 | H7: =ROUND(F7/G7,0) -> 596 | I7: =G7*H7 -> 30008.6 | J7: 180.5 | K7: =0.5*H7*J7 -> 53789 | L7: =VLOOKUP(A7,LivePrices!$A$4:$B$15,2,FALSE()) -> 137.1 | M7: =0.5*H7*L7 -> 40855.8 | N7: =IF(H7<=100,10,IF(H7<=200,20,IF(H7<=500,30,50))) -> 50 | O7: =(K7+M7)-(I7+N7) -> 64586.2 | P7: =MAX(0,$K$3*(K7-0.5*I7)) -> 5817.705 | Q7: =O7/I7 -> 2.1522564 | R7: =(O7-P7)/I7 -> 1.9583884 | S7: =K7+M7 -> 94644.8
A8: NVDA | B8: Information Technology | C8: Semiconductors | D8: NVIDIA (Information Technology - Semiconductors) makes GPUs for gaming and is now the dominant supplier of AI accelerator chips, driving explosive data-center revenue growth since 2023. | E8: 0.14 | F8: =$B$3*E8 -> 70000 | G8: 6.16 | H8: =ROUND(F8/G8,0) -> 11364 | I8: =G8*H8 -> 70002.24 | J8: 142.25 | K8: =0.5*H8*J8 -> 808264.5 | L8: =VLOOKUP(A8,LivePrices!$A$4:$B$15,2,FALSE()) -> 225.07 | M8: =0.5*H8*L8 -> 1278847.7 | N8: =IF(H8<=100,10,IF(H8<=200,20,IF(H8<=500,30,50))) -> 50 | O8: =(K8+M8)-(I8+N8) -> 2017060 | P8: =MAX(0,$K$3*(K8-0.5*I8)) -> 115989.51 | Q8: =O8/I8 -> 28.814221 | R8: =(O8-P8)/I8 -> 27.157281 | S8: =K8+M8 -> 2087112.2
A9: AMD | B9: Information Technology | C9: Semiconductors | D9: AMD (Information Technology - Semiconductors) designs CPUs and GPUs for PCs, servers, and data centers, competing with Intel in processors and NVIDIA in AI accelerators. | E9: 0.08 | F9: =$B$3*E9 -> 40000 | G9: 51.05 | H9: =ROUND(F9/G9,0) -> 784 | I9: =G9*H9 -> 40023.2 | J9: 122.84 | K9: =0.5*H9*J9 -> 48153.28 | L9: =VLOOKUP(A9,LivePrices!$A$4:$B$15,2,FALSE()) -> 630.63 | M9: =0.5*H9*L9 -> 247206.96 | N9: =IF(H9<=100,10,IF(H9<=200,20,IF(H9<=500,30,50))) -> 50 | O9: =(K9+M9)-(I9+N9) -> 255287.04 | P9: =MAX(0,$K$3*(K9-0.5*I9)) -> 4221.252 | Q9: =O9/I9 -> 6.3784765 | R9: =(O9-P9)/I9 -> 6.2730064 | S9: =K9+M9 -> 295360.24
A10: CRM | B10: Information Technology | C10: Software—Application | D10: Salesforce (Information Technology - Software—Application) is the world's largest CRM software provider, helping businesses manage sales, marketing, and service through its cloud platform. | E10: 0.07 | F10: =$B$3*E10 -> 35000 | G10: 181.8 | H10: =ROUND(F10/G10,0) -> 193 | I10: =G10*H10 -> 35087.4 | J10: 329.46 | K10: =0.5*H10*J10 -> 31792.89 | L10: =VLOOKUP(A10,LivePrices!$A$4:$B$15,2,FALSE()) -> 234.02 | M10: =0.5*H10*L10 -> 22582.93 | N10: =IF(H10<=100,10,IF(H10<=200,20,IF(H10<=500,30,50))) -> 20 | O10: =(K10+M10)-(I10+N10) -> 19268.42 | P10: =MAX(0,$K$3*(K10-0.5*I10)) -> 2137.3785 | Q10: =O10/I10 -> 0.54915497 | R10: =(O10-P10)/I10 -> 0.48823913 | S10: =K10+M10 -> 54375.82
A11: ADBE | B11: Information Technology | C11: Software—Application | D11: Adobe (Information Technology - Software—Application) makes creative software (Photoshop, Illustrator, Premiere) sold via Creative Cloud subscriptions, and has invested heavily in generative AI (Firefly). | E11: 0.06 | F11: =$B$3*E11 -> 30000 | G11: 350 | H11: =ROUND(F11/G11,0) -> 86 | I11: =G11*H11 -> 30100 | J11: 435.38 | K11: =0.5*H11*J11 -> 18721.34 | L11: =VLOOKUP(A11,LivePrices!$A$4:$B$15,2,FALSE()) -> 235.47 | M11: =0.5*H11*L11 -> 10125.21 | N11: =IF(H11<=100,10,IF(H11<=200,20,IF(H11<=500,30,50))) -> 10 | O11: =(K11+M11)-(I11+N11) -> -1263.45 | P11: =MAX(0,$K$3*(K11-0.5*I11)) -> 550.701 | Q11: =O11/I11 -> -0.041975083 | R11: =(O11-P11)/I11 -> -0.060270797 | S11: =K11+M11 -> 28846.55
A12: ACN | B12: Information Technology | C12: IT Services | D12: Accenture (Information Technology - IT Services) provides consulting, technology, and outsourcing services worldwide, helping clients with digital transformation and cloud migration. | E12: 0.04 | F12: =$B$3*E12 -> 20000 | G12: 186.15 | H12: =ROUND(F12/G12,0) -> 107 | I12: =G12*H12 -> 19918.05 | J12: 347.28 | K12: =0.5*H12*J12 -> 18579.48 | L12: =VLOOKUP(A12,LivePrices!$A$4:$B$15,2,FALSE()) -> 176.11 | M12: =0.5*H12*L12 -> 9421.885 | N12: =IF(H12<=100,10,IF(H12<=200,20,IF(H12<=500,30,50))) -> 20 | O12: =(K12+M12)-(I12+N12) -> 8063.315 | P12: =MAX(0,$K$3*(K12-0.5*I12)) -> 1293.0683 | Q12: =O12/I12 -> 0.40482452 | R12: =(O12-P12)/I12 -> 0.3399051 | S12: =K12+M12 -> 28001.365
A13: IBM | B13: Information Technology | C13: IT Services | D13: IBM (Information Technology - IT Services) offers hybrid cloud, AI (watsonx), and enterprise consulting, having pivoted toward software and services after acquiring Red Hat. | E13: 0.04 | F13: =$B$3*E13 -> 20000 | G13: 100.73 | H13: =ROUND(F13/G13,0) -> 199 | I13: =G13*H13 -> 20045.27 | J13: 214.76 | K13: =0.5*H13*J13 -> 21368.62 | L13: =VLOOKUP(A13,LivePrices!$A$4:$B$15,2,FALSE()) -> 225.51 | M13: =0.5*H13*L13 -> 22438.245 | N13: =IF(H13<=100,10,IF(H13<=200,20,IF(H13<=500,30,50))) -> 20 | O13: =(K13+M13)-(I13+N13) -> 23741.595 | P13: =MAX(0,$K$3*(K13-0.5*I13)) -> 1701.8978 | Q13: =O13/I13 -> 1.1843989 | R13: =(O13-P13)/I13 -> 1.0994962 | S13: =K13+M13 -> 43806.865
A14: JNJ | B14: Healthcare | C14: Drug Manufacturers—General | D14: Johnson & Johnson (Healthcare - Drug Manufacturers—General) focuses on pharmaceuticals and medical devices, covering oncology, immunology, and neuroscience, with consistent dividend growth. | E14: 0.12 | F14: =$B$3*E14 -> 60000 | G14: 124.07 | H14: =ROUND(F14/G14,0) -> 484 | I14: =G14*H14 -> 60049.88 | J14: 140.19 | K14: =0.5*H14*J14 -> 33925.98 | L14: =VLOOKUP(A14,LivePrices!$A$4:$B$15,2,FALSE()) -> 271.22 | M14: =0.5*H14*L14 -> 65635.24 | N14: =IF(H14<=100,10,IF(H14<=200,20,IF(H14<=500,30,50))) -> 30 | O14: =(K14+M14)-(I14+N14) -> 39481.34 | P14: =MAX(0,$K$3*(K14-0.5*I14)) -> 585.156 | Q14: =O14/I14 -> 0.65747575 | R14: =(O14-P14)/I14 -> 0.64773125 | S14: =K14+M14 -> 99561.22
A15: PFE | B15: Healthcare | C15: Drug Manufacturers—General | D15: Pfizer (Healthcare - Drug Manufacturers—General) is a leading global pharmaceutical company known for its COVID-19 vaccine and a broad portfolio spanning oncology, vaccines, and rare diseases. | E15: 0.05 | F15: =$B$3*E15 -> 25000 | G15: 27.4 | H15: =ROUND(F15/G15,0) -> 912 | I15: =G15*H15 -> 24988.8 | J15: 23.52 | K15: =0.5*H15*J15 -> 10725.12 | L15: =VLOOKUP(A15,LivePrices!$A$4:$B$15,2,FALSE()) -> 28.67 | M15: =0.5*H15*L15 -> 13073.52 | N15: =IF(H15<=100,10,IF(H15<=200,20,IF(H15<=500,30,50))) -> 50 | O15: =(K15+M15)-(I15+N15) -> -1240.16 | P15: =MAX(0,$K$3*(K15-0.5*I15)) -> 0 | Q15: =O15/I15 -> -0.049628634 | R15: =(O15-P15)/I15 -> -0.049628634 | S15: =K15+M15 -> 23798.64
A16: UNH | B16: Healthcare | C16: Healthcare Plans | D16: UnitedHealth Group (Healthcare - Healthcare Plans) is the largest U.S. health insurer; through UnitedHealthcare and Optum it provides insurance, pharmacy benefits, and care-delivery services. | E16: 0.13 | F16: =$B$3*E16 -> 65000 | G16: 267.26 | H16: =ROUND(F16/G16,0) -> 243 | I16: =G16*H16 -> 64944.18 | J16: 509.64 | K16: =0.5*H16*J16 -> 61921.26 | L16: =VLOOKUP(A16,LivePrices!$A$4:$B$15,2,FALSE()) -> 376.59 | M16: =0.5*H16*L16 -> 45755.685 | N16: =IF(H16<=100,10,IF(H16<=200,20,IF(H16<=500,30,50))) -> 30 | O16: =(K16+M16)-(I16+N16) -> 42702.765 | P16: =MAX(0,$K$3*(K16-0.5*I16)) -> 4417.3755 | Q16: =O16/I16 -> 0.65753028 | R16: =(O16-P16)/I16 -> 0.58951225 | S16: =K16+M16 -> 107676.95
A17: CI | B17: Healthcare | C17: Healthcare Plans | D17: Cigna (Healthcare - Healthcare Plans) provides health insurance and pharmacy benefit management (Evernorth), serving employers, government programs, and individuals worldwide. | E17: 0.05 | F17: =$B$3*E17 -> 25000 | G17: 191.55 | H17: =ROUND(F17/G17,0) -> 131 | I17: =G17*H17 -> 25093.05 | J17: 282.89 | K17: =0.5*H17*J17 -> 18529.295 | L17: =VLOOKUP(A17,LivePrices!$A$4:$B$15,2,FALSE()) -> 272.01 | M17: =0.5*H17*L17 -> 17816.655 | N17: =IF(H17<=100,10,IF(H17<=200,20,IF(H17<=500,30,50))) -> 20 | O17: =(K17+M17)-(I17+N17) -> 11232.9 | P17: =MAX(0,$K$3*(K17-0.5*I17)) -> 897.4155 | Q17: =O17/I17 -> 0.44764985 | R17: =(O17-P17)/I17 -> 0.41188634 | S17: =K17+M17 -> 36345.95
A18: TOTAL / PORTFOLIO AVERAGE | E18: =SUM(E6:E17) -> 0.96 | F18: =SUM(F6:F17) -> 480000 | I18: =SUM(I6:I17) -> 480269.05 | K18: =SUM(K6:K17) -> 1209434.5 | M18: =SUM(M6:M17) -> 1872348.3 | N18: =SUM(N6:N17) -> 380 | O18: =SUM(O6:O17) -> 2601133.8 | P18: =SUM(P6:P17) -> 145660.39 | Q18: =O18/I18 -> 5.4159929 | R18: =(O18-P18)/I18 -> 5.1127038 | S18: =SUM(S6:S17) -> 3081782.8
A19: CASH (Uninvested) | E19: =1-E18 -> 0.04 | F19: =$B$3*E19 -> 20000
A21: Allocation check (should equal 100%): | E21: =E18+E19 -> 1
A23: Note: Column S (Total Current Value) supports the chart below and is not one of the graded columns A–R.

Sheet LivePrices
A1: LIVE STOCK PRICES
A2: Feeds Portfolio!L via VLOOKUP. In live Excel: select the Ticker column, set Data Type = Stocks, insert the Price field, and refresh via Data > Refresh All.
A3: Ticker | B3: Live Price | C3: As Of | D3: Source / Method
A4: MSFT | B4: 516.17 | C4: 46292 | D4: Market data provider (Stock Data Type equivalent) – see Documentation PDF
A5: ORCL | B5: 137.1 | C5: 46292 | D5: Market data provider (Stock Data Type equivalent) – see Documentation PDF
A6: NVDA | B6: 225.07 | C6: 46292 | D6: Market data provider (Stock Data Type equivalent) – see Documentation PDF
A7: AMD | B7: 630.63 | C7: 46292 | D7: Market data provider (Stock Data Type equivalent) – see Documentation PDF
A8: CRM | B8: 234.02 | C8: 46292 | D8: Market data provider (Stock Data Type equivalent) – see Documentation PDF
A9: ADBE | B9: 235.47 | C9: 46292 | D9: Market data provider (Stock Data Type equivalent) – see Documentation PDF
A10: ACN | B10: 176.11 | C10: 46292 | D10: Market data provider (Stock Data Type equivalent) – see Documentation PDF
A11: IBM | B11: 225.51 | C11: 46292 | D11: Market data provider (Stock Data Type equivalent) – see Documentation PDF
A12: JNJ | B12: 271.22 | C12: 46292 | D12: Market data provider (Stock Data Type equivalent) – see Documentation PDF
A13: PFE | B13: 28.67 | C13: 46292 | D13: Market data provider (Stock Data Type equivalent) – see Documentation PDF
A14: UNH | B14: 376.59 | C14: 46292 | D14: Market data provider (Stock Data Type equivalent) – see Documentation PDF
A15: CI | B15: 272.01 | C15: 46292 | D15: Market data provider (Stock Data Type equivalent) – see Documentation PDF

Sheet Industry Pivot
A1: INDUSTRY-LEVEL SUMMARY
A2: Summary by Industry, built with SUMIFS/AVERAGEIFS off the Portfolio table (can also be built as an Insert > PivotTable from PortfolioData).
A4: Industry | B4: Total Invested ($) | C4: Total Gain ($) | D4: Avg % Gain
A5: Software—Infrastructure | B5: =SUMIFS(Portfolio!$I$6:$I$17,Portfolio!$C$6:$C$17,$A5) -> 90016.98 | C5: =SUMIFS(Portfolio!$O$6:$O$17,Portfolio!$C$6:$C$17,$A5) -> 186800.02 | D5: =AVERAGEIFS(Portfolio!$Q$6:$Q$17,Portfolio!$C$6:$C$17,$A5) -> 2.0944345
A6: Semiconductors | B6: =SUMIFS(Portfolio!$I$6:$I$17,Portfolio!$C$6:$C$17,$A6) -> 110025.44 | C6: =SUMIFS(Portfolio!$O$6:$O$17,Portfolio!$C$6:$C$17,$A6) -> 2272347 | D6: =AVERAGEIFS(Portfolio!$Q$6:$Q$17,Portfolio!$C$6:$C$17,$A6) -> 17.596349
A7: Software—Application | B7: =SUMIFS(Portfolio!$I$6:$I$17,Portfolio!$C$6:$C$17,$A7) -> 65187.4 | C7: =SUMIFS(Portfolio!$O$6:$O$17,Portfolio!$C$6:$C$17,$A7) -> 18004.97 | D7: =AVERAGEIFS(Portfolio!$Q$6:$Q$17,Portfolio!$C$6:$C$17,$A7) -> 0.25358994
A8: IT Services | B8: =SUMIFS(Portfolio!$I$6:$I$17,Portfolio!$C$6:$C$17,$A8) -> 39963.32 | C8: =SUMIFS(Portfolio!$O$6:$O$17,Portfolio!$C$6:$C$17,$A8) -> 31804.91 | D8: =AVERAGEIFS(Portfolio!$Q$6:$Q$17,Portfolio!$C$6:$C$17,$A8) -> 0.79461169
A9: Drug Manufacturers—General | B9: =SUMIFS(Portfolio!$I$6:$I$17,Portfolio!$C$6:$C$17,$A9) -> 85038.68 | C9: =SUMIFS(Portfolio!$O$6:$O$17,Portfolio!$C$6:$C$17,$A9) -> 38241.18 | D9: =AVERAGEIFS(Portfolio!$Q$6:$Q$17,Portfolio!$C$6:$C$17,$A9) -> 0.30392356
A10: Healthcare Plans | B10: =SUMIFS(Portfolio!$I$6:$I$17,Portfolio!$C$6:$C$17,$A10) -> 90037.23 | C10: =SUMIFS(Portfolio!$O$6:$O$17,Portfolio!$C$6:$C$17,$A10) -> 53935.665 | D10: =AVERAGEIFS(Portfolio!$Q$6:$Q$17,Portfolio!$C$6:$C$17,$A10) -> 0.55259006
A11: TOTAL | B11: =SUM(B5:B10) -> 480269.05 | C11: =SUM(C5:C10) -> 2601133.8 | D11: =AVERAGE(D5:D10) -> 3.5992497

Sheet Sector Pivot
A1: SECTOR-LEVEL SUMMARY
A2: Summary by Sector, built with SUMIFS/AVERAGEIFS off the Portfolio table (can also be built as an Insert > PivotTable from PortfolioData).
A4: Sector | B4: Total Invested ($) | C4: Total Gain ($) | D4: Avg % Gain
A5: Information Technology | B5: =SUMIFS(Portfolio!$I$6:$I$17,Portfolio!$B$6:$B$17,$A5) -> 305193.14 | C5: =SUMIFS(Portfolio!$O$6:$O$17,Portfolio!$B$6:$B$17,$A5) -> 2508956.9 | D5: =AVERAGEIFS(Portfolio!$Q$6:$Q$17,Portfolio!$B$6:$B$17,$A5) -> 5.1847462
A6: Healthcare | B6: =SUMIFS(Portfolio!$I$6:$I$17,Portfolio!$B$6:$B$17,$A6) -> 175075.91 | C6: =SUMIFS(Portfolio!$O$6:$O$17,Portfolio!$B$6:$B$17,$A6) -> 92176.845 | D6: =AVERAGEIFS(Portfolio!$Q$6:$Q$17,Portfolio!$B$6:$B$17,$A6) -> 0.42825681
A7: TOTAL | B7: =SUM(B5:B6) -> 480269.05 | C7: =SUM(C5:C6) -> 2601133.8 | D7: =AVERAGE(D5:D6) -> 2.8065015

Sheet Rebalance Simulation
A1: PORTFOLIO REBALANCING SIMULATION — 3-YEAR STRATEGY
A2: Rebalance date: Jan 24, 2023 (regular trading day, no holiday adjustment needed). The 6 stocks with the lowest total return since the Jan 21, 2020 purchase are sold at their Jan 24, 2023 price; proceeds are split equally and reinvested into the 6 top performers. The resulting position is held to the Jan 24, 2025 sell date, valued the same way as Parts 1-4 (Shares x Price).
A3: Rebalance Date: | B3: 44950
A5: Ticker | B5: Shares (Original Purchase) | C5: Purchase Price (Jan 21, 2020) | D5: Price at Rebalance (Jan 24, 2023) | E5: Value at Rebalance | F5: Return Since Purchase | G5: Rank (1=best) | H5: Status | I5: Sale Proceeds (Bottom 6) | J5: Reinvestment (Top 6, equal split) | K5: Additional Shares Bought | L5: New Total Shares | M5: Price at Sell (Jan 24, 2025) | N5: New Value at Sell Date
A6: =Portfolio!A6 -> MSFT | B6: =Portfolio!H6 -> 382 | C6: =Portfolio!G6 -> 157.09 | D6: 234.9 | E6: =B6*D6 -> 89731.8 | F6: =D6/C6-1 -> 0.49532115 | G6: =RANK(F6,$F$6:$F$17,0) -> 5 | H6: =IF(G6<=6,"KEEP (Top 6)","SOLD (Bottom 6)") -> KEEP (Top 6) | I6: =IF(H6="SOLD (Bottom 6)",E6,0) -> 0 | J6: =IF(H6="KEEP (Top 6)",$H$21,0) -> 36367.212 | K6: =IF(H6="KEEP (Top 6)",ROUND(J6/D6,0),0) -> 155 | L6: =IF(H6="KEEP (Top 6)",B6+K6,0) -> 537 | M6: =Portfolio!J6 -> 438.03 | N6: =L6*M6 -> 235222.11
A7: =Portfolio!A7 -> ORCL | B7: =Portfolio!H7 -> 596 | C7: =Portfolio!G7 -> 50.35 | D7: 85.91 | E7: =B7*D7 -> 51202.36 | F7: =D7/C7-1 -> 0.70625621 | G7: =RANK(F7,$F$6:$F$17,0) -> 3 | H7: =IF(G7<=6,"KEEP (Top 6)","SOLD (Bottom 6)") -> KEEP (Top 6) | I7: =IF(H7="SOLD (Bottom 6)",E7,0) -> 0 | J7: =IF(H7="KEEP (Top 6)",$H$21,0) -> 36367.212 | K7: =IF(H7="KEEP (Top 6)",ROUND(J7/D7,0),0) -> 423 | L7: =IF(H7="KEEP (Top 6)",B7+K7,0) -> 1019 | M7: =Portfolio!J7 -> 180.5 | N7: =L7*M7 -> 183929.5
A8: =Portfolio!A8 -> NVDA | B8: =Portfolio!H8 -> 11364 | C8: =Portfolio!G8 -> 6.16 | D8: 19.2 | E8: =B8*D8 -> 218188.8 | F8: =D8/C8-1 -> 2.1168831 | G8: =RANK(F8,$F$6:$F$17,0) -> 1 | H8: =IF(G8<=6,"KEEP (Top 6)","SOLD (Bottom 6)") -> KEEP (Top 6) | I8: =IF(H8="SOLD (Bottom 6)",E8,0) -> 0 | J8: =IF(H8="KEEP (Top 6)",$H$21,0) -> 36367.212 | K8: =IF(H8="KEEP (Top 6)",ROUND(J8/D8,0),0) -> 1894 | L8: =IF(H8="KEEP (Top 6)",B8+K8,0) -> 13258 | M8: =Portfolio!J8 -> 142.25 | N8: =L8*M8 -> 1885950.5
A9: =Portfolio!A9 -> AMD | B9: =Portfolio!H9 -> 784 | C9: =Portfolio!G9 -> 51.05 | D9: 74.7 | E9: =B9*D9 -> 58564.8 | F9: =D9/C9-1 -> 0.4632713 | G9: =RANK(F9,$F$6:$F$17,0) -> 6 | H9: =IF(G9<=6,"KEEP (Top 6)","SOLD (Bottom 6)") -> KEEP (Top 6) | I9: =IF(H9="SOLD (Bottom 6)",E9,0) -> 0 | J9: =IF(H9="KEEP (Top 6)",$H$21,0) -> 36367.212 | K9: =IF(H9="KEEP (Top 6)",ROUND(J9/D9,0),0) -> 487 | L9: =IF(H9="KEEP (Top 6)",B9+K9,0) -> 1271 | M9: =Portfolio!J9 -> 122.84 | N9: =L9*M9 -> 156129.64
A10: =Portfolio!A10 -> CRM | B10: =Portfolio!H10 -> 193 | C10: =Portfolio!G10 -> 181.8 | D10: 151.96 | E10: =B10*D10 -> 29328.28 | F10: =D10/C10-1 -> -0.16413641 | G10: =RANK(F10,$F$6:$F$17,0) -> 12 | H10: =IF(G10<=6,"KEEP (Top 6)","SOLD (Bottom 6)") -> SOLD (Bottom 6) | I10: =IF(H10="SOLD (Bottom 6)",E10,0) -> 29328.28 | J10: =IF(H10="KEEP (Top 6)",$H$21,0) -> 0 | K10: =IF(H10="KEEP (Top 6)",ROUND(J10/D10,0),0) -> 0 | L10: =IF(H10="KEEP (Top 6)",B10+K10,0) -> 0 | M10: =Portfolio!J10 -> 329.46 | N10: =L10*M10 -> 0
A11: =Portfolio!A11 -> ADBE | B11: =Portfolio!H11 -> 86 | C11: =Portfolio!G11 -> 350 | D11: 361.32 | E11: =B11*D11 -> 31073.52 | F11: =D11/C11-1 -> 0.032342857 | G11: =RANK(F11,$F$6:$F$17,0) -> 11 | H11: =IF(G11<=6,"KEEP (Top 6)","SOLD (Bottom 6)") -> SOLD (Bottom 6) | I11: =IF(H11="SOLD (Bottom 6)",E11,0) -> 31073.52 | J11: =IF(H11="KEEP (Top 6)",$H$21,0) -> 0 | K11: =IF(H11="KEEP (Top 6)",ROUND(J11/D11,0),0) -> 0 | L11: =IF(H11="KEEP (Top 6)",B11+K11,0) -> 0 | M11: =Portfolio!J11 -> 435.38 | N11: =L11*M11 -> 0
A12: =Portfolio!A12 -> ACN | B12: =Portfolio!H12 -> 107 | C12: =Portfolio!G12 -> 186.15 | D12: 255.13 | E12: =B12*D12 -> 27298.91 | F12: =D12/C12-1 -> 0.37056138 | G12: =RANK(F12,$F$6:$F$17,0) -> 7 | H12: =IF(G12<=6,"KEEP (Top 6)","SOLD (Bottom 6)") -> SOLD (Bottom 6) | I12: =IF(H12="SOLD (Bottom 6)",E12,0) -> 27298.91 | J12: =IF(H12="KEEP (Top 6)",$H$21,0) -> 0 | K12: =IF(H12="KEEP (Top 6)",ROUND(J12/D12,0),0) -> 0 | L12: =IF(H12="KEEP (Top 6)",B12+K12,0) -> 0 | M12: =Portfolio!J12 -> 347.28 | N12: =L12*M12 -> 0
A13: =Portfolio!A13 -> IBM | B13: =Portfolio!H13 -> 199 | C13: =Portfolio!G13 -> 100.73 | D13: 124.28 | E13: =B13*D13 -> 24731.72 | F13: =D13/C13-1 -> 0.23379331 | G13: =RANK(F13,$F$6:$F$17,0) -> 9 | H13: =IF(G13<=6,"KEEP (Top 6)","SOLD (Bottom 6)") -> SOLD (Bottom 6) | I13: =IF(H13="SOLD (Bottom 6)",E13,0) -> 24731.72 | J13: =IF(H13="KEEP (Top 6)",$H$21,0) -> 0 | K13: =IF(H13="KEEP (Top 6)",ROUND(J13/D13,0),0) -> 0 | L13: =IF(H13="KEEP (Top 6)",B13+K13,0) -> 0 | M13: =Portfolio!J13 -> 214.76 | N13: =L13*M13 -> 0
A14: =Portfolio!A14 -> JNJ | B14: =Portfolio!H14 -> 484 | C14: =Portfolio!G14 -> 124.07 | D14: 151.19 | E14: =B14*D14 -> 73175.96 | F14: =D14/C14-1 -> 0.21858628 | G14: =RANK(F14,$F$6:$F$17,0) -> 10 | H14: =IF(G14<=6,"KEEP (Top 6)","SOLD (Bottom 6)") -> SOLD (Bottom 6) | I14: =IF(H14="SOLD (Bottom 6)",E14,0) -> 73175.96 | J14: =IF(H14="KEEP (Top 6)",$H$21,0) -> 0 | K14: =IF(H14="KEEP (Top 6)",ROUND(J14/D14,0),0) -> 0 | L14: =IF(H14="KEEP (Top 6)",B14+K14,0) -> 0 | M14: =Portfolio!J14 -> 140.19 | N14: =L14*M14 -> 0
A15: =Portfolio!A15 -> PFE | B15: =Portfolio!H15 -> 912 | C15: =Portfolio!G15 -> 27.4 | D15: 35.74 | E15: =B15*D15 -> 32594.88 | F15: =D15/C15-1 -> 0.30437956 | G15: =RANK(F15,$F$6:$F$17,0) -> 8 | H15: =IF(G15<=6,"KEEP (Top 6)","SOLD (Bottom 6)") -> SOLD (Bottom 6) | I15: =IF(H15="SOLD (Bottom 6)",E15,0) -> 32594.88 | J15: =IF(H15="KEEP (Top 6)",$H$21,0) -> 0 | K15: =IF(H15="KEEP (Top 6)",ROUND(J15/D15,0),0) -> 0 | L15: =IF(H15="KEEP (Top 6)",B15+K15,0) -> 0 | M15: =Portfolio!J15 -> 23.52 | N15: =L15*M15 -> 0
A16: =Portfolio!A16 -> UNH | B16: =Portfolio!H16 -> 243 | C16: =Portfolio!G16 -> 267.26 | D16: 456.38 | E16: =B16*D16 -> 110900.34 | F16: =D16/C16-1 -> 0.70762553 | G16: =RANK(F16,$F$6:$F$17,0) -> 2 | H16: =IF(G16<=6,"KEEP (Top 6)","SOLD (Bottom 6)") -> KEEP (Top 6) | I16: =IF(H16="SOLD (Bottom 6)",E16,0) -> 0 | J16: =IF(H16="KEEP (Top 6)",$H$21,0) -> 36367.212 | K16: =IF(H16="KEEP (Top 6)",ROUND(J16/D16,0),0) -> 80 | L16: =IF(H16="KEEP (Top 6)",B16+K16,0) -> 323 | M16: =Portfolio!J16 -> 509.64 | N16: =L16*M16 -> 164613.72
A17: =Portfolio!A17 -> CI | B17: =Portfolio!H17 -> 131 | C17: =Portfolio!G17 -> 191.55 | D17: 287.62 | E17: =B17*D17 -> 37678.22 | F17: =D17/C17-1 -> 0.50154007 | G17: =RANK(F17,$F$6:$F$17,0) -> 4 | H17: =IF(G17<=6,"KEEP (Top 6)","SOLD (Bottom 6)") -> KEEP (Top 6) | I17: =IF(H17="SOLD (Bottom 6)",E17,0) -> 0 | J17: =IF(H17="KEEP (Top 6)",$H$21,0) -> 36367.212 | K17: =IF(H17="KEEP (Top 6)",ROUND(J17/D17,0),0) -> 126 | L17: =IF(H17="KEEP (Top 6)",B17+K17,0) -> 257 | M17: =Portfolio!J17 -> 282.89 | N17: =L17*M17 -> 72702.73
A18: TOTAL | E18: =SUM(E6:E17) -> 784469.59 | I18: =SUM(I6:I17) -> 218203.27 | N18: =SUM(N6:N17) -> 2698548.2
A21: Reinvestment per Top-6 Stock ($): | H21: =I18/6 -> 36367.212
A23: Buy & Hold Value - No Rebalancing (Jan 24, 2025): | H23: =SUMPRODUCT(B6:B17,M6:M17) -> 2418869
A24: Rebalanced Portfolio Value (Jan 24, 2025): | H24: =N18 -> 2698548.2
A25: Rebalancing Benefit ($): | H25: =H24-H23 -> 279679.21
A26: Rebalancing Benefit (%): | H26: =H24/H23-1 -> 0.11562396
A28: Note: Column D (price at rebalance) is a sourced historical input, like Purchase Price and Sell Price on the Portfolio sheet. All ranking, selection, proceeds, and valuation logic is formula-driven.
